pymov2gif/__init__.py
pymov2gif/__main__.py
pymov2gif/_version.py
pymov2gif-0.0.3.dist-info/METADATA
pymov2gif-0.0.3.dist-info/WHEEL
pymov2gif-0.0.3.dist-info/entry_points.txt
pymov2gif-0.0.3.dist-info/licenses/LICENSE
pymov2gif-0.0.3.dist-info/RECORD
