Metadata-Version: 2.4
Name: pymov2gif
Version: 0.0.3
Summary: Convert *.mov to *.gif
Project-URL: Homepage, https://github.com/jan-janssen/pymov2gif
Author-email: Jan Janssen <jan.janssen@outlook.com>
License: BSD-3-Clause
License-File: LICENSE
Requires-Python: >=3.7
